{
    "@context": {
        "schema": "http://schema.org/",
        "dc": "http://purl.org/dc/terms/"
    },
    "@graph": [
        {
            "@type": "schema:ResearchProject",
            "schema:identifier": "72816@test",
            "schema:publicKey": "51e4ef67c8468080de202021cdf53740020213ae369a1aca4df71dd2bec04947",
            "schema:description": {
                "@context": {
                    "schema": "http://schema.org/",
                    "dc": "http://purl.org/dc/terms/"
                },
                "@type": "schema:ResearchProject",
                "schema:name": "Investigating the Role of climate change in urban development",
                "dc:abstract": "This study explores the impact of climate change in urban development, focusing on pollution mitigation.",
                "schema:keywords": [
                    "climate change",
                    "urban development",
                    "pollution mitigation"
                ],
                "schema:startDate": "2021-07-21",
                "schema:endDate": "2028-02-26",
                "schema:funding": {
                    "@type": "schema:Organization",
                    "schema:name": "World Wildlife Fund"
                },
                "schema:location": {
                    "@type": "schema:Place",
                    "schema:name": "Lisbon, Portugal"
                }
            },
            "schema:metadataCID": "QmTP58bKjLiD3BLfYRYXUqEgoHnNuYrKozsSkB9UxBZPUY",
            "schema:linked_user": "sleepy_ptolemy@test",
            "schema:files": [
                {
                    "file_index": 1,
                    "file_cid": "QmXquoApMLCcauNkz4tYw1Sp2tsqZ4edv1YtnQi5pmbw6C",
                    "metadata_cid": "QmNfwXmL4R1ToJzYuucj1L1HYxrDvNAcJKVtywYWhLRmsg",
                    "metadata": {
                        "dc:format": "application/pdf; version=1.7",
                        "dc:title": "Mel Spectrogram-based advanced deep temporal clustering model with unsupervised data for fault diagnosis",
                        "dc:creator": "Geonkyo Hong",
                        "dcterms:created": "2023-02-07T18:16:11Z",
                        "dcterms:modified": "2023-02-07T18:19:55Z",
                        "dc:language": "en",
                        "dc:subject": [
                            "Anomaly detection,Data augmentation,Fault diagnosis,Mel spectrogram,Time series,Unsupervised learning",
                            "Expert Systems With Applications, 217 (2023) 119551. doi:10.1016/j.eswa.2023.119551"
                        ]
                    }
                }
            ]
        },
        {
            "@type": "schema:ResearchProject",
            "schema:identifier": "94773@test",
            "schema:publicKey": "e70e99ad0384c9b104c09767d45c33732b7a4ea26cf0e755fba5f6bed781f3e4",
            "schema:description": {
                "@context": {
                    "schema": "http://schema.org/",
                    "dc": "http://purl.org/dc/terms/"
                },
                "@type": "schema:ResearchProject",
                "schema:name": "Analyzing the Influence of digital twins on climate adaptation",
                "dc:abstract": "This paper analyzes how digital twins influences climate adaptation, providing insights into how to maximize its risk mitigation.",
                "schema:keywords": [
                    "digital twins",
                    "climate adaptation",
                    "risk mitigation"
                ],
                "schema:startDate": "2020-11-28",
                "schema:endDate": "2026-08-02",
                "schema:funding": {
                    "@type": "schema:Organization",
                    "schema:name": "European Union Horizon 2020"
                },
                "schema:location": {
                    "@type": "schema:Place",
                    "schema:name": "Rotterdam, Netherlands"
                }
            },
            "schema:metadataCID": "QmefzDgsYwqAivmC9wdso56VqE4vsgk2Af2fRHcaop38bA",
            "schema:linked_user": "unruffled_borg@test",
            "schema:files": [
                {
                    "file_index": 1,
                    "file_cid": "QmdiRawzVNUiB28ENKQ7WefeFLEJ1xMjsJjwtHL2jnJ9xW",
                    "metadata_cid": "QmUProyRppTaJkyFQqXRXfznUKKLRmuRDcd7FLiP9wjB5N",
                    "metadata": {
                        "dc:format": "application/pdf; version=1.6",
                        "dc:title": "The reproducibility debate is an opportunity, not a crisis",
                        "dc:description": "BMC Research Notes, https://doi.org/10.1186/s13104-022-05942-3",
                        "dc:creator": [
                            "Marcus R. Munaf\u00f2 ",
                            "Chris Chambers ",
                            "Alexandra Collins ",
                            "Laura Fortunato ",
                            "Malcolm Macleod "
                        ],
                        "dcterms:created": "2022-02-04T06:52:19Z",
                        "dcterms:modified": "2022-02-10T12:46:46Z",
                        "dc:language": "EN",
                        "dc:subject": [
                            "UK Reproducibility Network,Reproducibility,Replicability,Research Integrity",
                            "BMC Research Notes, https://doi.org/10.1186/s13104-022-05942-3"
                        ]
                    }
                }
            ]
        },
        {
            "@type": "schema:ResearchProject",
            "schema:identifier": "66781@test",
            "schema:publicKey": "84d9f4ef320d3bc29d8ed10ef3d969fe4b742f73642fb8134d4701a8a619f91e",
            "schema:description": {
                "@context": {
                    "schema": "http://schema.org/",
                    "dc": "http://purl.org/dc/terms/"
                },
                "@type": "schema:ResearchProject",
                "schema:name": "Analyzing the Influence of robotics on energy storage",
                "dc:abstract": "This paper analyzes how robotics influences energy storage, providing insights into how to maximize its improved decision-making.",
                "schema:keywords": [
                    "robotics",
                    "energy storage",
                    "improved decision-making"
                ],
                "schema:startDate": "2021-10-17",
                "schema:endDate": "2027-08-06",
                "schema:funding": {
                    "@type": "schema:Organization",
                    "schema:name": "National Institutes of Health"
                },
                "schema:location": {
                    "@type": "schema:Place",
                    "schema:name": "Berlin, Germany"
                }
            },
            "schema:metadataCID": "QmQU69GdRR5yLLHvtMAf4jZ66V1VX2RZRVHbCyfUE869RK",
            "schema:linked_user": "angry_nightingale@test",
            "schema:files": [
                {
                    "file_index": 1,
                    "file_cid": "QmV1vYkuiwKGPA5Tyi4ECNFfWYocyTtQ3E5j7CSvPBX49Q",
                    "metadata_cid": "QmX21jh1qKTV5CaywcnWpkhYiDGi3xwpJHXQqf7XbSsLwD",
                    "metadata": {
                        "dc:format": "application/pdf; version=1.7",
                        "dc:title": "Deep learning in insurance: Accuracy and model interpretability using TabNet",
                        "dc:description": "Expert Systems With Applications, 217 (2023) 119543. doi:10.1016/j.eswa.2023.119543",
                        "dc:creator": [
                            "Kevin McDonnell",
                            "Finbarr Murphy",
                            "Barry Sheehan",
                            "Leandro Masello",
                            "German Castignani"
                        ],
                        "dcterms:created": "2023-02-04T09:40:15Z",
                        "dcterms:modified": "2023-02-07T17:36:19Z",
                        "dc:language": "en",
                        "dc:subject": [
                            "Deep Learning,Telematics,Connected Vehicles,Insurance,General Linear Model,XGBoost,Machine Learning,Explainable AI",
                            "Expert Systems With Applications, 217 (2023) 119543. doi:10.1016/j.eswa.2023.119543"
                        ]
                    }
                }
            ]
        },
        {
            "@type": "schema:ResearchProject",
            "schema:identifier": "40254@test",
            "schema:publicKey": "1b6e0b6c5140c3568ec14622a4abd4207bdf1ee9735c4ebeece35c4c53ba7462",
            "schema:description": {
                "@context": {
                    "schema": "http://schema.org/",
                    "dc": "http://purl.org/dc/terms/"
                },
                "@type": "schema:ResearchProject",
                "schema:name": "Analyzing the Influence of satellite imagery on energy storage",
                "dc:abstract": "This paper analyzes how satellite imagery influences energy storage, providing insights into how to maximize its personalized medicine.",
                "schema:keywords": [
                    "satellite imagery",
                    "energy storage",
                    "personalized medicine"
                ],
                "schema:startDate": "2021-06-22",
                "schema:endDate": "2026-09-03",
                "schema:funding": {
                    "@type": "schema:Organization",
                    "schema:name": "Bill and Melinda Gates Foundation"
                },
                "schema:location": {
                    "@type": "schema:Place",
                    "schema:name": "Kigali, Rwanda"
                }
            },
            "schema:metadataCID": "QmZsuhLpbQRd8purkymaLyKgyw3DmsCSmLSB4Eri72fFtS",
            "schema:linked_user": "frosty_cole@test",
            "schema:files": [
                {
                    "file_index": 1,
                    "file_cid": "QmT7ximApXtExAedhzUHGHDwRismRzuKykpH4dgTvGrNZs",
                    "metadata_cid": "QmVqzuk7KUpXhJacCkZCRJgvYMemR56cx26TcrEnk1peXD",
                    "metadata": {
                        "dc:format": "application/pdf; version=1.7",
                        "dc:title": "Diabetic retinopathy identification using parallel convolutional neural network based feature extractor and ELM classifier",
                        "dc:description": "Expert Systems With Applications, 217 (2023) 119557. doi:10.1016/j.eswa.2023.119557",
                        "dc:creator": [
                            "Md. Nahiduzzaman",
                            "Md. Robiul Islam",
                            "Md. Omaer Faruq Goni",
                            "Md. Shamim Anower",
                            "Mominul Ahsan",
                            "Julfikar Haider",
                            "Marcin Kowalski"
                        ],
                        "dcterms:created": "2023-02-04T09:40:15Z",
                        "dcterms:modified": "2023-02-07T17:54:35Z",
                        "dc:language": "en",
                        "dc:subject": [
                            "Contrast limited adaptive histogram equalization (CLAHE),Diabetic retinopathy (DR),Parallel convolutional neural network (PCNN),Extreme LEARNING MACHine (ELM)",
                            "Expert Systems With Applications, 217 (2023) 119557. doi:10.1016/j.eswa.2023.119557"
                        ]
                    }
                }
            ]
        }
    ]
}